Metadata-Version: 2.1
Name: darkapi
Version: 0.1
Summary: Использование функций форума через python
Home-page: UNKNOWN
Author-email: cotanton111@gmail.com
License: UNKNOWN
Platform: UNKNOWN
